LICENSE.txt
MANIFEST.in
README.md
setup.cfg
setup.py
easyforms/__init__.py
easyforms/advancedfields.py
easyforms/basicfields.py
easyforms/bs4.py
easyforms/cmsfields.py
easyforms/config.py
easyforms/dbfields.py
easyforms/env.py
easyforms/exceptions.py
easyforms/form.py
easyforms/formtype.py
easyforms/styles.py
easyforms/validate.py
easyforms.egg-info/PKG-INFO
easyforms.egg-info/SOURCES.txt
easyforms.egg-info/dependency_links.txt
easyforms.egg-info/requires.txt
easyforms.egg-info/top_level.txt
easyforms/templates/ef_basic_input.html
easyforms/templates/ef_macros.html
easyforms/templates/form.html
easyforms/templates/form_section.html
easyforms/templates/advanced/ckeditor.html
easyforms/templates/advanced/colour.html
easyforms/templates/advanced/date_picker.html
easyforms/templates/advanced/date_select.html
easyforms/templates/advanced/date_time.html
easyforms/templates/advanced/deprecated_html_field.html
easyforms/templates/advanced/enum_select.html
easyforms/templates/advanced/file_upload.html
easyforms/templates/advanced/filemanager.html
easyforms/templates/advanced/gender.html
easyforms/templates/advanced/getaddress_postcode_field.html
easyforms/templates/advanced/multi_submit.html
easyforms/templates/advanced/multicheckbox.html
easyforms/templates/advanced/recaptcha.html
easyforms/templates/advanced/shipping_method.html
easyforms/templates/advanced/submit_cancel.html
easyforms/templates/advanced/time_input.html
easyforms/templates/advanced/year_month_select.html
easyforms/templates/basic/.select.html.swp
easyforms/templates/basic/checkbox.html
easyforms/templates/basic/hidden_input.html
easyforms/templates/basic/radios.html
easyforms/templates/basic/select.html
easyforms/templates/basic/submit.html
easyforms/templates/basic/text_area.html
easyforms/templates/cms/ckeditor.html
test/test_easyforms.py