Metadata-Version: 1.1
Name: easyforms
Version: 0.1.24
Summary: Form processing library for Flask and Jinja2
Home-page: https://github.com/stevelittlefish/easyforms
Author: Stephen Brown (Little Fish Solutions LTD)
Author-email: opensource@littlefish.solutions
License: Apache
Download-URL: https://github.com/stevelittlefish/easyforms/archive/v0.1.24.tar.gz
Keywords: flask,forms,jinja2,easy
Platform: UNKNOWN
Classifier: License :: OSI Approved :: Apache Software License
Classifier: Framework :: Flask
Classifier: Development Status :: 5 - Production/Stable
Classifier: Intended Audience :: Developers
Classifier: Programming Language :: Python :: 3
Classifier: Topic :: Software Development :: Libraries
